{"State.ff4f336e-da4a-4443-aaab-84999accbcdb": {"id": "ff4f336e-da4a-4443-aaab-84999accbcdb", "created_at": "2021-03-29T12:53:21.631854", "updated_at": "2021-03-29T12:53:21.631857", "name": "California", "__class__": "State"}, "State.6a932ff2-3977-4c30-b9e5-751933948f82": {"id": "6a932ff2-3977-4c30-b9e5-751933948f82", "created_at": "2021-03-29T12:53:21.632046", "updated_at": "2021-03-29T12:53:21.632047", "name": "Arizona", "__class__": "State"}, "Place.3ae5ff81-ff45-4e89-bdfd-35e5ed315fb9": {"id": "3ae5ff81-ff45-4e89-bdfd-35e5ed315fb9", "created_at": "2021-03-29T12:53:21.632273", "updated_at": "2021-03-29T12:53:21.632274", "city_id": "0001", "user_id": "0001", "name": "My little house", "number_rooms": 4, "number_bathrooms": 2, "max_guest": 10, "price_by_night": 300, "latitude": 37.773972, "longitude": -122.431297, "__class__": "Place"}}